obhavo/__init__.py
obhavo/obhavo.py
WeatherUzbekistan-0.0.1.dist-info/METADATA
WeatherUzbekistan-0.0.1.dist-info/WHEEL
WeatherUzbekistan-0.0.1.dist-info/top_level.txt
WeatherUzbekistan-0.0.1.dist-info/RECORD
