Metadata-Version: 2.1
Name: WeatherUzbekistan
Version: 0.0.1
Summary: Bu o'zbekiston ob havosi haqida malumot beradigan kutubxona
Author: Sino Farmonv
Classifier: Programming Language :: Python :: 3
Classifier: License :: OSI Approved :: MIT License
Requires-Dist: requests
Requires-Dist: beautifulsoup4
